LICENSE.txt
README.md
setup.py
dynamics/CMM.py
dynamics/__init__.py
dynamics/apply_external_forces.py
dynamics/continuous_dynamics/ContinuousDynamics.py
dynamics/continuous_dynamics/CoriolisAndGravityTerms.py
dynamics/continuous_dynamics/EnergyAndMomentum.py
dynamics/continuous_dynamics/HandC.py
dynamics/continuous_dynamics/__init__.py
dynamics/dynamical_system/DynamicalSystem.py
dynamics/dynamical_system/__init__.py
models/__init__.py
models/floatbase.py
pyRBDA.egg-info/PKG-INFO
pyRBDA.egg-info/SOURCES.txt
pyRBDA.egg-info/dependency_links.txt
pyRBDA.egg-info/requires.txt
pyRBDA.egg-info/top_level.txt
spatial/EnerMo.py
spatial/FDab.py
spatial/FDcrb.py
spatial/FDfb.py
spatial/FDgq.py
spatial/Fpt.py
spatial/HD.py
spatial/He.py
spatial/ID.py
spatial/IDfb.py
spatial/InertiaMatrix.py
spatial/LTDL.py
spatial/LTL.py
spatial/Vpt.py
spatial/Xpt.py
spatial/XtoV.py
spatial/__init__.py
spatial/crf.py
spatial/crm.py
spatial/expandLambda.py
spatial/fbanim.py
spatial/fbkin.py
spatial/floatbase.py
spatial/get_gravity.py
spatial/jcalc.py
spatial/mcI.py
spatial/mpyH.py
spatial/mpyL.py
spatial/mpyLi.py
spatial/mpyLit.py
spatial/mpyLt.py
spatial/plnr.py
spatial/pluho.py
spatial/plux.py
spatial/rotx.py
spatial/roty.py
spatial/rotz.py
spatial/rq.py
spatial/rqd.py
spatial/rv.py
spatial/rx.py
spatial/ry.py
spatial/rz.py
spatial/skew.py
spatial/xlt.py