Metadata-Version: 2.1
Name: pyRBDA
Version: 0.1.1
Summary: Rigid-body spatial math in Python
Home-page: https://github.com/prem-chand/pyspatial
Author: PC
Author-email: premc946@gmail.com
License: UNKNOWN
Platform: UNKNOWN
Classifier: Programming Language :: Python :: 3
Classifier: License :: OSI Approved :: GNU General Public License v3 (GPLv3)
Classifier: Operating System :: OS Independent
Requires-Python: >=3.6
License-File: LICENSE.txt
